MANIFEST.in
README.md
setup.py
SeqTweet.egg-info/PKG-INFO
SeqTweet.egg-info/SOURCES.txt
SeqTweet.egg-info/dependency_links.txt
SeqTweet.egg-info/requires.txt
SeqTweet.egg-info/top_level.txt
seqtweet/__init__.py
seqtweet/auth.py
seqtweet/creds.py
seqtweet/seqtweet.py