Metadata-Version: 1.0
Name: SeqTweet
Version: 0.1
Summary: Stores arbitrary strings on Twitter by implementing linked         lists.
Home-page: https://github.com/workmajj/seqtweet
Author: John J. Workman
Author-email: workman@alumni.duke.edu
License: BSD 3-Clause <http://www.opensource.org/licenses/BSD-3-Clause>
Platform: UNKNOWN
Classifier: Development Status :: 3 - Alpha
Classifier: Topic :: Internet
